myneta/cli.py
myneta-0.0.1.dist-info/LICENSE
myneta-0.0.1.dist-info/WHEEL
myneta-0.0.1.dist-info/METADATA
myneta-0.0.1.dist-info/RECORD
