Metadata-Version: 2.1
Name: myneta
Version: 0.0.1
Summary: A CLI to interact/extract data from myneta
License: MIT
Author: kracekumar
Author-email: me@kracekumar.com
Requires-Python: >=3.9,<4.0
Classifier: License :: OSI Approved :: MIT License
Classifier: Programming Language :: Python :: 3
Classifier: Programming Language :: Python :: 3.9
Requires-Dist: beautifulsoup4 (>=4.9.3,<5.0.0)
Requires-Dist: click (>=7.1.2,<8.0.0)
Requires-Dist: html5lib (>=1.1,<2.0)
Requires-Dist: ipython (>=7.22.0,<8.0.0)
Requires-Dist: lxml (>=4.6.3,<5.0.0)
Requires-Dist: pandas (>=1.2.3,<2.0.0)
Requires-Dist: requests (>=2.25.1,<3.0.0)
